read_unicode_environment_variables_dictionary.py
read_unicode_environment_variables_dictionary-0.1.0a0.dist-info/licenses/LICENSE
read_unicode_environment_variables_dictionary-0.1.0a0.dist-info/METADATA
read_unicode_environment_variables_dictionary-0.1.0a0.dist-info/WHEEL
read_unicode_environment_variables_dictionary-0.1.0a0.dist-info/top_level.txt
read_unicode_environment_variables_dictionary-0.1.0a0.dist-info/RECORD
