Metadata-Version: 2.4
Name: read-unicode-environment-variables-dictionary
Version: 0.1.0a0
Summary: Use raw ctypes to read Unicode environment variables directly from the OS, even where Python's own `os` module is incomplete or restricted.
Author-email: Jifeng Wu <jifengwu2k@gmail.com>
License-Expression: MIT
Project-URL: Homepage, https://github.com/jifengwu2k/read-unicode-environment-variables-dictionary
Project-URL: Bug Tracker, https://github.com/jifengwu2k/read-unicode-environment-variables-dictionary/issues
Classifier: Programming Language :: Python :: 2
Classifier: Programming Language :: Python :: 3
Classifier: Operating System :: OS Independent
Requires-Python: >=2
License-File: LICENSE
Requires-Dist: posix-or-nt
Requires-Dist: typing; python_version < "3.5"
Dynamic: license-file
